LICENSE
README.md
setup.py
datalab/Matrix.py
datalab/Vector.py
datalab/__init__.py
datalab/functions.py
datalab/utils.py
py_datalab.egg-info/PKG-INFO
py_datalab.egg-info/SOURCES.txt
py_datalab.egg-info/dependency_links.txt
py_datalab.egg-info/requires.txt
py_datalab.egg-info/top_level.txt