Metadata-Version: 2.1
Name: py-datalab
Version: 0.2.4
Summary: This project provides classes for working with data in python. Actually there are two classes: Matrix and Vector.
Home-page: https://github.com/matuszen/Python-DataLab
Author: Mateusz Nowak
Author-email: mateusz.nowak.pol@gmail.com
Classifier: Development Status :: 3 - Alpha
Classifier: License :: OSI Approved :: MIT License
Classifier: Programming Language :: Python
Classifier: Programming Language :: Python :: 3
Classifier: Programming Language :: Python :: 3 :: Only
Classifier: Programming Language :: Python :: 3.10
Classifier: Programming Language :: Python :: 3.11
Classifier: Operating System :: Microsoft :: Windows
Classifier: Operating System :: POSIX
Classifier: Operating System :: Unix
Classifier: Operating System :: MacOS
License-File: LICENSE
